Workbook

Sheet Selection lists
A1: Test Scope | B1: Tax rate | C1: WACC (EUR) | F1: Fiscal Year
A2: Austria | B2: 0.25 | C2: 0.054816128 | F2: 2017
A3: Belgium | B3: 0.3399 | C3: 0.056456072 | F3: =F2+1 -> 2018
A4: Bulgaria | B4: 0.1 | C4: 0.075810783 | F4: =F3+1 -> 2019
A5: China | B5: 0.25 | C5: 0.057104545 | F5: =F4+1 -> 2020
A6: Synthetic Test Scope | B6: 0.26938687 | C6: 0.058104425 | F6: =F5+1 -> 2021
A7: Croatia | B7: 0.2 | C7: 0.084555324 | F7: =F6+1 -> 2022
A8: Czech Republic | B8: 0.19 | C8: 0.05832484 | F8: =F7+1 -> 2023
A9: Denmark | B9: 0.235 | C9: 0.053040794 | F9: =F8+1 -> 2024
A10: Egypt | B10: 0.25 | C10: 0.095867045 | F10: =F9+1 -> 2025
A11: France | B11: 0.38 | C11: 0.053739129 | F11: =F10+1 -> 2026
A12: Germany | B12: 0.3053 | C12: 0.050259168 | F12: =F11+1 -> 2027
A13: Greece | B13: 0.26 | C13: 0.12151508 | F13: =F12+1 -> 2028
A14: Hong Kong | B14: 0.165 | C14: 0.052464205 | F14: =F13+1 -> 2029
... A20: Kazakhstan | B20: 0.2 | C20: 0.075472434 | F20: =F19+1 -> 2035
A21: Luxemburg | F21: =F20+1 -> 2036
A22: Malaysia | B22: 0.25 | C22: 0.056630342 | F22: =F21+1 -> 2037
A23: Moldova | B23: 0.12 | C23: 0.10145742 | F23: =F22+1 -> 2038
A24: Netherlands | B24: 0.25 | C24: 0.053516462 | F24: =F23+1 -> 2039
A25: Pakistan | B25: 0.32 | C25: 0.094380134 | F25: =F24+1 -> 2040
A26: Philippines | B26: 0.3 | C26: 0.060270466 | F26: =F25+1 -> 2041
A27: Poland | B27: 0.19 | C27: 0.062366299 | F27: =F26+1 -> 2042
A28: Portugal | B28: 0.225 | C28: 0.09390747 | F28: =F27+1 -> 2043
A29: Romania | B29: 0.16 | C29: 0.073951188 | F29: =F28+1 -> 2044
A30: Russia | B30: 0.2 | C30: 0.073235124 | F30: =F29+1 -> 2045
A31: Serbia | B31: 0.15 | C31: 0.085361703 | F31: =F30+1 -> 2046
A32: Singapore | B32: 0.17 | C32: 0.052385622 | F32: =F31+1 -> 2047
A33: Slovakia | B33: 0.22 | C33: 0.060149429 | F33: =F32+1 -> 2048
A34: Spain | B34: 0.28 | C34: 0.071304394 | F34: =F33+1 -> 2049
A35: Switzerland | F35: =F34+1 -> 2050
A36: Thailand | B36: 0.2 | C36: 0.059521125 | F36: =F35+1 -> 2051
A37: Turkey | B37: 0.2 | C37: 0.074621124 | F37: =F36+1 -> 2052
A38: Ukraine | B38: 0.18 | C38: 0.11474546 | F38: =F37+1 -> 2053
A39: Vietnam | B39: 0.22 | C39: 0.097343479 | F39: =F38+1 -> 2054

Sheet Upload
A1: 0 | B1: Fiscal year | C1: Type of Cash Out | D1: Short Description | E1: ='Costs & Benefits'!J31 -> 2026 | F1: ='Costs & Benefits'!K31 -> 2027 | G1: ='Costs & Benefits'!L31 -> 2028 | H1: ='Costs & Benefits'!M31 -> 2029 | I1: ='Costs & Benefits'!N31 -> 2030 | J1: ='Costs & Benefits'!O31 -> 2031 | K1: ='Costs & Benefits'!P31 -> 2032 | L1: ='Costs & Benefits'!Q31 -> 2033 | ... N1: ='Costs & Benefits'!S31 -> 2035
A2: 1 | B2: SC 70 - Project Capitalizable (intern) | C2: ='Costs & Benefits'!H19 -> One-Off | D2: ='Costs & Benefits'!I19 -> Synthetic internal solution and test-design effort | E2: =IF('Costs & Benefits'!J19,'Costs & Benefits'!J19,"") -> 150000 | F2: =IF('Costs & Benefits'!K19,'Costs & Benefits'!K19,"") | G2: =IF('Costs & Benefits'!L19,'Costs & Benefits'!L19,"") | H2: =IF('Costs & Benefits'!M19,'Costs & Benefits'!M19,"") | I2: =IF('Costs & Benefits'!N19,'Costs & Benefits'!N19,"") | J2: =IF('Costs & Benefits'!O19,'Costs & Benefits'!O19,"") | K2: =IF('Costs & Benefits'!P19,'Costs & Benefits'!P19,"") | L2: =IF('Costs & Benefits'!Q19,'Costs & Benefits'!Q19,"") | ... N2: =IF('Costs & Benefits'!S19,'Costs & Benefits'!S19,"")
A3: 2 | B3: SC 70 - Project Capitalizable (extern) | C3: ='Costs & Benefits'!H20 -> One-Off | D3: ='Costs & Benefits'!I20 -> Synthetic external implementation effort | E3: =IF('Costs & Benefits'!J20,'Costs & Benefits'!J20,"") -> 250000 | F3: =IF('Costs & Benefits'!K20,'Costs & Benefits'!K20,"") | G3: =IF('Costs & Benefits'!L20,'Costs & Benefits'!L20,"") | H3: =IF('Costs & Benefits'!M20,'Costs & Benefits'!M20,"") | I3: =IF('Costs & Benefits'!N20,'Costs & Benefits'!N20,"") | J3: =IF('Costs & Benefits'!O20,'Costs & Benefits'!O20,"") | K3: =IF('Costs & Benefits'!P20,'Costs & Benefits'!P20,"") | L3: =IF('Costs & Benefits'!Q20,'Costs & Benefits'!Q20,"") | ... N3: =IF('Costs & Benefits'!S20,'Costs & Benefits'!S20,"")
A4: 3 | B4: SC 90 - Software Licenses (intern) | C4: ='Costs & Benefits'!H22 -> One-Off | D4: ='Costs & Benefits'!I22 -> Test integration licences and tooling | E4: =IF('Costs & Benefits'!J22,'Costs & Benefits'!J22,"") -> 50000 | F4: =IF('Costs & Benefits'!K22,'Costs & Benefits'!K22,"") | G4: =IF('Costs & Benefits'!L22,'Costs & Benefits'!L22,"") | H4: =IF('Costs & Benefits'!M22,'Costs & Benefits'!M22,"") | I4: =IF('Costs & Benefits'!N22,'Costs & Benefits'!N22,"") | J4: =IF('Costs & Benefits'!O22,'Costs & Benefits'!O22,"") | K4: =IF('Costs & Benefits'!P22,'Costs & Benefits'!P22,"") | L4: =IF('Costs & Benefits'!Q22,'Costs & Benefits'!Q22,"") | ... N4: =IF('Costs & Benefits'!S22,'Costs & Benefits'!S22,"")
A5: 4 | B5: Local IT/IM Investments (extern) | C5: ='Costs & Benefits'!H24 -> One-Off | D5: ='Costs & Benefits'!I24 -> Synthetic test-environment setup | E5: =IF('Costs & Benefits'!J24,'Costs & Benefits'!J24,"") -> 30000 | F5: =IF('Costs & Benefits'!K24,'Costs & Benefits'!K24,"") | G5: =IF('Costs & Benefits'!L24,'Costs & Benefits'!L24,"") | H5: =IF('Costs & Benefits'!M24,'Costs & Benefits'!M24,"") | I5: =IF('Costs & Benefits'!N24,'Costs & Benefits'!N24,"") | J5: =IF('Costs & Benefits'!O24,'Costs & Benefits'!O24,"") | K5: =IF('Costs & Benefits'!P24,'Costs & Benefits'!P24,"") | L5: =IF('Costs & Benefits'!Q24,'Costs & Benefits'!Q24,"") | ... N5: =IF('Costs & Benefits'!S24,'Costs & Benefits'!S24,"")
A6: 5 | B6: SC 10 - Project Non Capitalizable (intern) | C6: ='Costs & Benefits'!H34 -> One-Off | D6: ='Costs & Benefits'!I34 -> Internal test onboarding and enablement | E6: =IF('Costs & Benefits'!J34,'Costs & Benefits'!J34,"") -> 50000 | F6: =IF('Costs & Benefits'!K34,'Costs & Benefits'!K34,"") | G6: =IF('Costs & Benefits'!L34,'Costs & Benefits'!L34,"") | H6: =IF('Costs & Benefits'!M34,'Costs & Benefits'!M34,"") | I6: =IF('Costs & Benefits'!N34,'Costs & Benefits'!N34,"") | J6: =IF('Costs & Benefits'!O34,'Costs & Benefits'!O34,"") | K6: =IF('Costs & Benefits'!P34,'Costs & Benefits'!P34,"") | L6: =IF('Costs & Benefits'!Q34,'Costs & Benefits'!Q34,"") | ... N6: =IF('Costs & Benefits'!S34,'Costs & Benefits'!S34,"")
A7: 6 | B7: SC 10 - Project Non Capitalizable (extern) | C7: ='Costs & Benefits'!H35 -> One-Off | D7: ='Costs & Benefits'!I35 -> External test rollout and documentation support | E7: =IF('Costs & Benefits'!J35,'Costs & Benefits'!J35,"") -> 50000 | F7: =IF('Costs & Benefits'!K35,'Costs & Benefits'!K35,"") | G7: =IF('Costs & Benefits'!L35,'Costs & Benefits'!L35,"") | H7: =IF('Costs & Benefits'!M35,'Costs & Benefits'!M35,"") | I7: =IF('Costs & Benefits'!N35,'Costs & Benefits'!N35,"") | J7: =IF('Costs & Benefits'!O35,'Costs & Benefits'!O35,"") | K7: =IF('Costs & Benefits'!P35,'Costs & Benefits'!P35,"") | L7: =IF('Costs & Benefits'!Q35,'Costs & Benefits'!Q35,"") | ... N7: =IF('Costs & Benefits'!S35,'Costs & Benefits'!S35,"")
A8: 7 | B8: SC 30 - Maint. and Support (intern) | C8: ='Costs & Benefits'!H37 -> Recurrent | D8: ='Costs & Benefits'!I37 -> Internal test platform support | E8: =IF('Costs & Benefits'!J37,'Costs & Benefits'!J37,"") | F8: =IF('Costs & Benefits'!K37,'Costs & Benefits'!K37,"") -> 20000 | G8: =IF('Costs & Benefits'!L37,'Costs & Benefits'!L37,"") -> 20000 | H8: =IF('Costs & Benefits'!M37,'Costs & Benefits'!M37,"") -> 20000 | I8: =IF('Costs & Benefits'!N37,'Costs & Benefits'!N37,"") -> 20000 | J8: =IF('Costs & Benefits'!O37,'Costs & Benefits'!O37,"") -> 20000 | K8: =IF('Costs & Benefits'!P37,'Costs & Benefits'!P37,"") -> 20000 | L8: =IF('Costs & Benefits'!Q37,'Costs & Benefits'!Q37,"") -> 20000 | ... N8: =IF('Costs & Benefits'!S37,'Costs & Benefits'!S37,"") -> 20000
A9: 8 | B9: SC 30 - SaaS (extern) | C9: ='Costs & Benefits'!H39 -> Recurrent | D9: ='Costs & Benefits'!I39 -> Test messaging and automation services | E9: =IF('Costs & Benefits'!J39,'Costs & Benefits'!J39,"") | F9: =IF('Costs & Benefits'!K39,'Costs & Benefits'!K39,"") -> 35000 | G9: =IF('Costs & Benefits'!L39,'Costs & Benefits'!L39,"") -> 35000 | H9: =IF('Costs & Benefits'!M39,'Costs & Benefits'!M39,"") -> 35000 | I9: =IF('Costs & Benefits'!N39,'Costs & Benefits'!N39,"") -> 35000 | J9: =IF('Costs & Benefits'!O39,'Costs & Benefits'!O39,"") -> 35000 | K9: =IF('Costs & Benefits'!P39,'Costs & Benefits'!P39,"") -> 35000 | L9: =IF('Costs & Benefits'!Q39,'Costs & Benefits'!Q39,"") -> 35000 | ... N9: =IF('Costs & Benefits'!S39,'Costs & Benefits'!S39,"") -> 35000
A10: 9 | B10: SC 30 - Maint. for ext. SW Licenses (extern) | C10: ='Costs & Benefits'!H41 -> Recurrent | D10: ='Costs & Benefits'!I41 -> External maintenance for test integrations | E10: =IF('Costs & Benefits'!J41,'Costs & Benefits'!J41,"") | F10: =IF('Costs & Benefits'!K41,'Costs & Benefits'!K41,"") -> 20000 | G10: =IF('Costs & Benefits'!L41,'Costs & Benefits'!L41,"") -> 20000 | H10: =IF('Costs & Benefits'!M41,'Costs & Benefits'!M41,"") -> 20000 | I10: =IF('Costs & Benefits'!N41,'Costs & Benefits'!N41,"") -> 20000 | J10: =IF('Costs & Benefits'!O41,'Costs & Benefits'!O41,"") -> 20000 | K10: =IF('Costs & Benefits'!P41,'Costs & Benefits'!P41,"") -> 20000 | L10: =IF('Costs & Benefits'!Q41,'Costs & Benefits'!Q41,"") -> 20000 | ... N10: =IF('Costs & Benefits'!S41,'Costs & Benefits'!S41,"") -> 20000
A11: 10 | B11: SC 40 - IOS (intern) | C11: ='Costs & Benefits'!H43 -> Recurrent | D11: ='Costs & Benefits'!I43 -> 0 | E11: =IF('Costs & Benefits'!J43,'Costs & Benefits'!J43,"") | F11: =IF('Costs & Benefits'!K43,'Costs & Benefits'!K43,"") | G11: =IF('Costs & Benefits'!L43,'Costs & Benefits'!L43,"") | H11: =IF('Costs & Benefits'!M43,'Costs & Benefits'!M43,"") | I11: =IF('Costs & Benefits'!N43,'Costs & Benefits'!N43,"") | J11: =IF('Costs & Benefits'!O43,'Costs & Benefits'!O43,"") | K11: =IF('Costs & Benefits'!P43,'Costs & Benefits'!P43,"") | L11: =IF('Costs & Benefits'!Q43,'Costs & Benefits'!Q43,"") | ... N11: =IF('Costs & Benefits'!S43,'Costs & Benefits'!S43,"")
A12: 11 | B12: SC 50 - AS (intern) | C12: ='Costs & Benefits'!H45 -> Recurrent | D12: ='Costs & Benefits'!I45 -> 0 | E12: =IF('Costs & Benefits'!J45,'Costs & Benefits'!J45,"") | F12: =IF('Costs & Benefits'!K45,'Costs & Benefits'!K45,"") | G12: =IF('Costs & Benefits'!L45,'Costs & Benefits'!L45,"") | H12: =IF('Costs & Benefits'!M45,'Costs & Benefits'!M45,"") | I12: =IF('Costs & Benefits'!N45,'Costs & Benefits'!N45,"") | J12: =IF('Costs & Benefits'!O45,'Costs & Benefits'!O45,"") | K12: =IF('Costs & Benefits'!P45,'Costs & Benefits'!P45,"") | L12: =IF('Costs & Benefits'!Q45,'Costs & Benefits'!Q45,"") | ... N12: =IF('Costs & Benefits'!S45,'Costs & Benefits'!S45,"")
A13: 12 | B13: Local IT/IM Costs One-Off (intern) | C13: ='Costs & Benefits'!H47 -> One-Off | D13: ='Costs & Benefits'!I47 -> 0 | E13: =IF('Costs & Benefits'!J47,'Costs & Benefits'!J47,"") | F13: =IF('Costs & Benefits'!K47,'Costs & Benefits'!K47,"") | G13: =IF('Costs & Benefits'!L47,'Costs & Benefits'!L47,"") | H13: =IF('Costs & Benefits'!M47,'Costs & Benefits'!M47,"") | I13: =IF('Costs & Benefits'!N47,'Costs & Benefits'!N47,"") | J13: =IF('Costs & Benefits'!O47,'Costs & Benefits'!O47,"") | K13: =IF('Costs & Benefits'!P47,'Costs & Benefits'!P47,"") | L13: =IF('Costs & Benefits'!Q47,'Costs & Benefits'!Q47,"") | ... N13: =IF('Costs & Benefits'!S47,'Costs & Benefits'!S47,"")
A14: 13 | B14: Local IT/IM Costs Recurr. (intern) | C14: ='Costs & Benefits'!H48 -> Recurrent | D14: ='Costs & Benefits'!I48 -> 0 | E14: =IF('Costs & Benefits'!J48,'Costs & Benefits'!J48,"") | F14: =IF('Costs & Benefits'!K48,'Costs & Benefits'!K48,"") | G14: =IF('Costs & Benefits'!L48,'Costs & Benefits'!L48,"") | H14: =IF('Costs & Benefits'!M48,'Costs & Benefits'!M48,"") | I14: =IF('Costs & Benefits'!N48,'Costs & Benefits'!N48,"") | J14: =IF('Costs & Benefits'!O48,'Costs & Benefits'!O48,"") | K14: =IF('Costs & Benefits'!P48,'Costs & Benefits'!P48,"") | L14: =IF('Costs & Benefits'!Q48,'Costs & Benefits'!Q48,"") | ... N14: =IF('Costs & Benefits'!S48,'Costs & Benefits'!S48,"")
A15: 14 | B15: Sales Benefits | D15: ='Costs & Benefits'!I94 -> Synthetic incremental value from automated test journeys | E15: =IF('Costs & Benefits'!J94,'Costs & Benefits'!J94,"") | F15: =IF('Costs & Benefits'!K94,'Costs & Benefits'!K94,"") -> 200000 | G15: =IF('Costs & Benefits'!L94,'Costs & Benefits'!L94,"") -> 400000 | H15: =IF('Costs & Benefits'!M94,'Costs & Benefits'!M94,"") -> 600000 | I15: =IF('Costs & Benefits'!N94,'Costs & Benefits'!N94,"") -> 700000 | J15: =IF('Costs & Benefits'!O94,'Costs & Benefits'!O94,"") -> 700000 | K15: =IF('Costs & Benefits'!P94,'Costs & Benefits'!P94,"") -> 700000 | L15: =IF('Costs & Benefits'!Q94,'Costs & Benefits'!Q94,"") -> 700000 | ... N15: =IF('Costs & Benefits'!S94,'Costs & Benefits'!S94,"") -> 700000
A16: 15 | B16: Sales Benefits | D16: ='Costs & Benefits'!I95 -> 0 | E16: =IF('Costs & Benefits'!J95,'Costs & Benefits'!J95,"") | F16: =IF('Costs & Benefits'!K95,'Costs & Benefits'!K95,"") | G16: =IF('Costs & Benefits'!L95,'Costs & Benefits'!L95,"") | H16: =IF('Costs & Benefits'!M95,'Costs & Benefits'!M95,"") | I16: =IF('Costs & Benefits'!N95,'Costs & Benefits'!N95,"") | J16: =IF('Costs & Benefits'!O95,'Costs & Benefits'!O95,"") | K16: =IF('Costs & Benefits'!P95,'Costs & Benefits'!P95,"") | L16: =IF('Costs & Benefits'!Q95,'Costs & Benefits'!Q95,"") | ... N16: =IF('Costs & Benefits'!S95,'Costs & Benefits'!S95,"")
A17: 16 | B17: Sales Benefits | D17: ='Costs & Benefits'!I96 -> 0 | E17: =IF('Costs & Benefits'!J96,'Costs & Benefits'!J96,"") | F17: =IF('Costs & Benefits'!K96,'Costs & Benefits'!K96,"") | G17: =IF('Costs & Benefits'!L96,'Costs & Benefits'!L96,"") | H17: =IF('Costs & Benefits'!M96,'Costs & Benefits'!M96,"") | I17: =IF('Costs & Benefits'!N96,'Costs & Benefits'!N96,"") | J17: =IF('Costs & Benefits'!O96,'Costs & Benefits'!O96,"") | K17: =IF('Costs & Benefits'!P96,'Costs & Benefits'!P96,"") | L17: =IF('Costs & Benefits'!Q96,'Costs & Benefits'!Q96,"") | ... N17: =IF('Costs & Benefits'!S96,'Costs & Benefits'!S96,"")
A18: 17 | B18: Sales Benefits | D18: ='Costs & Benefits'!I97 -> 0 | E18: =IF('Costs & Benefits'!J97,'Costs & Benefits'!J97,"") | F18: =IF('Costs & Benefits'!K97,'Costs & Benefits'!K97,"") | G18: =IF('Costs & Benefits'!L97,'Costs & Benefits'!L97,"") | H18: =IF('Costs & Benefits'!M97,'Costs & Benefits'!M97,"") | I18: =IF('Costs & Benefits'!N97,'Costs & Benefits'!N97,"") | J18: =IF('Costs & Benefits'!O97,'Costs & Benefits'!O97,"") | K18: =IF('Costs & Benefits'!P97,'Costs & Benefits'!P97,"") | L18: =IF('Costs & Benefits'!Q97,'Costs & Benefits'!Q97,"") | ... N18: =IF('Costs & Benefits'!S97,'Costs & Benefits'!S97,"")
A19: 18 | B19: Sales Benefits | D19: ='Costs & Benefits'!I98 -> 0 | E19: =IF('Costs & Benefits'!J98,'Costs & Benefits'!J98,"") | F19: =IF('Costs & Benefits'!K98,'Costs & Benefits'!K98,"") | G19: =IF('Costs & Benefits'!L98,'Costs & Benefits'!L98,"") | H19: =IF('Costs & Benefits'!M98,'Costs & Benefits'!M98,"") | I19: =IF('Costs & Benefits'!N98,'Costs & Benefits'!N98,"") | J19: =IF('Costs & Benefits'!O98,'Costs & Benefits'!O98,"") | K19: =IF('Costs & Benefits'!P98,'Costs & Benefits'!P98,"") | L19: =IF('Costs & Benefits'!Q98,'Costs & Benefits'!Q98,"") | ... N19: =IF('Costs & Benefits'!S98,'Costs & Benefits'!S98,"")
A20: 19 | B20: Sales Benefits | D20: ='Costs & Benefits'!I99 -> 0 | E20: =IF('Costs & Benefits'!J99,'Costs & Benefits'!J99,"") | F20: =IF('Costs & Benefits'!K99,'Costs & Benefits'!K99,"") | G20: =IF('Costs & Benefits'!L99,'Costs & Benefits'!L99,"") | H20: =IF('Costs & Benefits'!M99,'Costs & Benefits'!M99,"") | I20: =IF('Costs & Benefits'!N99,'Costs & Benefits'!N99,"") | J20: =IF('Costs & Benefits'!O99,'Costs & Benefits'!O99,"") | K20: =IF('Costs & Benefits'!P99,'Costs & Benefits'!P99,"") | L20: =IF('Costs & Benefits'!Q99,'Costs & Benefits'!Q99,"") | ... N20: =IF('Costs & Benefits'!S99,'Costs & Benefits'!S99,"")
A21: 20 | B21: Cost Savings | D21: ='Costs & Benefits'!I106 -> Reduced manual setup effort in the test process | E21: =IF('Costs & Benefits'!J106,'Costs & Benefits'!J106,"") | F21: =IF('Costs & Benefits'!K106,'Costs & Benefits'!K106,"") -> 30000 | G21: =IF('Costs & Benefits'!L106,'Costs & Benefits'!L106,"") -> 60000 | H21: =IF('Costs & Benefits'!M106,'Costs & Benefits'!M106,"") -> 80000 | I21: =IF('Costs & Benefits'!N106,'Costs & Benefits'!N106,"") -> 80000 | J21: =IF('Costs & Benefits'!O106,'Costs & Benefits'!O106,"") -> 80000 | K21: =IF('Costs & Benefits'!P106,'Costs & Benefits'!P106,"") -> 80000 | L21: =IF('Costs & Benefits'!Q106,'Costs & Benefits'!Q106,"") -> 80000 | ... N21: =IF('Costs & Benefits'!S106,'Costs & Benefits'!S106,"") -> 80000
A22: 21 | B22: Cost Savings | D22: ='Costs & Benefits'!I107 -> Reduced duplicated test-template and integration effort | E22: =IF('Costs & Benefits'!J107,'Costs & Benefits'!J107,"") | F22: =IF('Costs & Benefits'!K107,'Costs & Benefits'!K107,"") -> 20000 | G22: =IF('Costs & Benefits'!L107,'Costs & Benefits'!L107,"") -> 40000 | H22: =IF('Costs & Benefits'!M107,'Costs & Benefits'!M107,"") -> 50000 | I22: =IF('Costs & Benefits'!N107,'Costs & Benefits'!N107,"") -> 50000 | J22: =IF('Costs & Benefits'!O107,'Costs & Benefits'!O107,"") -> 50000 | K22: =IF('Costs & Benefits'!P107,'Costs & Benefits'!P107,"") -> 50000 | L22: =IF('Costs & Benefits'!Q107,'Costs & Benefits'!Q107,"") -> 50000 | ... N22: =IF('Costs & Benefits'!S107,'Costs & Benefits'!S107,"") -> 50000
A23: 22 | B23: Cost Savings | D23: ='Costs & Benefits'!I108 -> 0 | E23: =IF('Costs & Benefits'!J108,'Costs & Benefits'!J108,"") | F23: =IF('Costs & Benefits'!K108,'Costs & Benefits'!K108,"") | G23: =IF('Costs & Benefits'!L108,'Costs & Benefits'!L108,"") | H23: =IF('Costs & Benefits'!M108,'Costs & Benefits'!M108,"") | I23: =IF('Costs & Benefits'!N108,'Costs & Benefits'!N108,"") | J23: =IF('Costs & Benefits'!O108,'Costs & Benefits'!O108,"") | K23: =IF('Costs & Benefits'!P108,'Costs & Benefits'!P108,"") | L23: =IF('Costs & Benefits'!Q108,'Costs & Benefits'!Q108,"") | ... N23: =IF('Costs & Benefits'!S108,'Costs & Benefits'!S108,"")
A24: 23 | B24: Cost Savings | D24: ='Costs & Benefits'!I109 -> 0 | E24: =IF('Costs & Benefits'!J109,'Costs & Benefits'!J109,"") | F24: =IF('Costs & Benefits'!K109,'Costs & Benefits'!K109,"") | G24: =IF('Costs & Benefits'!L109,'Costs & Benefits'!L109,"") | H24: =IF('Costs & Benefits'!M109,'Costs & Benefits'!M109,"") | I24: =IF('Costs & Benefits'!N109,'Costs & Benefits'!N109,"") | J24: =IF('Costs & Benefits'!O109,'Costs & Benefits'!O109,"") | K24: =IF('Costs & Benefits'!P109,'Costs & Benefits'!P109,"") | L24: =IF('Costs & Benefits'!Q109,'Costs & Benefits'!Q109,"") | ... N24: =IF('Costs & Benefits'!S109,'Costs & Benefits'!S109,"")
A25: 24 | B25: Cost Savings | D25: ='Costs & Benefits'!I110 -> 0 | E25: =IF('Costs & Benefits'!J110,'Costs & Benefits'!J110,"") | F25: =IF('Costs & Benefits'!K110,'Costs & Benefits'!K110,"") | G25: =IF('Costs & Benefits'!L110,'Costs & Benefits'!L110,"") | H25: =IF('Costs & Benefits'!M110,'Costs & Benefits'!M110,"") | I25: =IF('Costs & Benefits'!N110,'Costs & Benefits'!N110,"") | J25: =IF('Costs & Benefits'!O110,'Costs & Benefits'!O110,"") | K25: =IF('Costs & Benefits'!P110,'Costs & Benefits'!P110,"") | L25: =IF('Costs & Benefits'!Q110,'Costs & Benefits'!Q110,"") | ... N25: =IF('Costs & Benefits'!S110,'Costs & Benefits'!S110,"")
A26: 25 | B26: Cost Savings | D26: ='Costs & Benefits'!I111 -> 0 | E26: =IF('Costs & Benefits'!J111,'Costs & Benefits'!J111,"") | F26: =IF('Costs & Benefits'!K111,'Costs & Benefits'!K111,"") | G26: =IF('Costs & Benefits'!L111,'Costs & Benefits'!L111,"") | H26: =IF('Costs & Benefits'!M111,'Costs & Benefits'!M111,"") | I26: =IF('Costs & Benefits'!N111,'Costs & Benefits'!N111,"") | J26: =IF('Costs & Benefits'!O111,'Costs & Benefits'!O111,"") | K26: =IF('Costs & Benefits'!P111,'Costs & Benefits'!P111,"") | L26: =IF('Costs & Benefits'!Q111,'Costs & Benefits'!Q111,"") | ... N26: =IF('Costs & Benefits'!S111,'Costs & Benefits'!S111,"")
A27: 26 | B27: Non-quantitative Benefits | D27: ='Costs & Benefits'!G117 -> Synthetic qualitative benefits: repeatable campaign tests; faster setup; consistent measurement; no use of production customer data.
A28: 27 | B28: EBIT per period | E28: =IF(Summary!I32,Summary!I32,"") -> -108000 | F28: =IF(Summary!J32,Summary!J32,"") -> 119000 | G28: =IF(Summary!K32,Summary!K32,"") -> 329000 | H28: =IF(Summary!L32,Summary!L32,"") -> 559000 | I28: =IF(Summary!M32,Summary!M32,"") -> 659000 | J28: =IF(Summary!N32,Summary!N32,"") -> 667000 | K28: =IF(Summary!O32,Summary!O32,"") -> 715000 | L28: =IF(Summary!P32,Summary!P32,"") -> 755000 | ... N28: =IF(Summary!R32,Summary!R32,"") -> 755000
A29: 28 | B29: Discounted EVA cumulative | E29: =IF(Summary!I41,Summary!I41,"") -> -83089.737 | F29: =IF(Summary!J41,Summary!J41,"") -> -23765.231 | G29: =IF(Summary!K41,Summary!K41,"") -> 179694.68 | H29: =IF(Summary!L41,Summary!L41,"") -> 577352.74 | I29: =IF(Summary!M41,Summary!M41,"") -> 914058.33 | J29: =IF(Summary!N41,Summary!N41,"") -> 1241123.8 | K29: =IF(Summary!O41,Summary!O41,"") -> 1558403.5 | L29: =IF(Summary!P41,Summary!P41,"") -> 1895441.1 | ... N29: =IF(Summary!R41,Summary!R41,"") -> 2578322.1
A30: 29 | B30: ROI (all years) | D30: =Summary!I53 -> 5.5803097
A31: 30 | B31: Payback Period | D31: ='Costs & Benefits'!I141 -> 21.251412
A32: 31 | B32: Project Number | D32: =Summary!J9 -> TEST-BC-003
A33: 32 | B33: Start FY | D33: =Summary!O10 -> 2026

Sheet Summary
G2: IT Business Case 2026 - SYNTHETIC TEST DATA | J2: =J10 -> PRODUCT 3 | Campaign Automation [TEST] | T2: ?
G3: Summary
I7: Test Scope | J7: Synthetic Test Scope | N7: Project Manager | O7: Test Project Manager C
I8: Test Decision ID | J8: 1003 | N8: Project Sponsor | O8: Test Sponsor C
I9: Project Number(s) | J9: TEST-BC-003 | N9: Creation date | O9: 46037
I10: Project Name | J10: PRODUCT 3 | Campaign Automation [TEST] | N10: Start (FY) | O10: 2026
I11: Program Name | J11: Synthetic Marketing Program C | N11: Go-Live (FY) | O11: 2027
F15: Fiscal year | I15: =O10 -> 2026 | J15: =O10+1 -> 2027 | K15: =O10+2 -> 2028 | L15: =O10+3 -> 2029 | M15: =O10+4 -> 2030 | N15: =O10+5 -> 2031 | O15: =O10+6 -> 2032 | P15: =O10+7 -> 2033 | Q15: =O10+8 -> 2034 | R15: =O10+9 -> 2035 | S15: Total
C16: I. Cost-Benefit Comparison
F17: Non-capitalizable efforts | I17: ='Costs & Benefits'!J50 -> 100000 | J17: ='Costs & Benefits'!K50 -> 75000 | K17: ='Costs & Benefits'!L50 -> 75000 | L17: ='Costs & Benefits'!M50 -> 75000 | M17: ='Costs & Benefits'!N50 -> 75000 | N17: ='Costs & Benefits'!O50 -> 75000 | O17: ='Costs & Benefits'!P50 -> 75000 | P17: ='Costs & Benefits'!Q50 -> 75000 | ... R17: ='Costs & Benefits'!S50 -> 75000 | S17: =SUM(I17:R17) -> 775000
F18: Depreciation | I18: ='Costs & Benefits'!J84 -> 8000 | J18: ='Costs & Benefits'!K84 -> 56000 | K18: ='Costs & Benefits'!L84 -> 96000 | L18: ='Costs & Benefits'!M84 -> 96000 | M18: ='Costs & Benefits'!N84 -> 96000 | N18: ='Costs & Benefits'!O84 -> 88000 | O18: ='Costs & Benefits'!P84 -> 40000 | P18: ='Costs & Benefits'!Q84 -> 0 | ... R18: ='Costs & Benefits'!S84 -> 0 | S18: =SUM(I18:R18) -> 480000
F19: Costs | I19: =I17+I18 -> 108000 | J19: =J17+J18 -> 131000 | K19: =K17+K18 -> 171000 | L19: =L17+L18 -> 171000 | M19: =M17+M18 -> 171000 | N19: =N17+N18 -> 163000 | O19: =O17+O18 -> 115000 | P19: =P17+P18 -> 75000 | ... R19: =R17+R18 -> 75000 | S19: =SUM(I19:R19) -> 1255000
F20: Sales benefits | I20: ='Costs & Benefits'!J101 -> 0 | J20: ='Costs & Benefits'!K101 -> 200000 | K20: ='Costs & Benefits'!L101 -> 400000 | L20: ='Costs & Benefits'!M101 -> 600000 | M20: ='Costs & Benefits'!N101 -> 700000 | N20: ='Costs & Benefits'!O101 -> 700000 | O20: ='Costs & Benefits'!P101 -> 700000 | P20: ='Costs & Benefits'!Q101 -> 700000 | ... R20: ='Costs & Benefits'!S101 -> 700000 | S20: =SUM(I20:R20) -> 5400000
F21: Cost savings | I21: ='Costs & Benefits'!J113 -> 0 | J21: ='Costs & Benefits'!K113 -> 50000 | K21: ='Costs & Benefits'!L113 -> 100000 | L21: ='Costs & Benefits'!M113 -> 130000 | M21: ='Costs & Benefits'!N113 -> 130000 | N21: ='Costs & Benefits'!O113 -> 130000 | O21: ='Costs & Benefits'!P113 -> 130000 | P21: ='Costs & Benefits'!Q113 -> 130000 | ... R21: ='Costs & Benefits'!S113 -> 130000 | S21: =SUM(I21:R21) -> 1060000
F22: Benefits | I22: =I20+I21 -> 0 | J22: =J20+J21 -> 250000 | K22: =K20+K21 -> 500000 | L22: =L20+L21 -> 730000 | M22: =M20+M21 -> 830000 | N22: =N20+N21 -> 830000 | O22: =O20+O21 -> 830000 | P22: =P20+P21 -> 830000 | ... R22: =R20+R21 -> 830000 | S22: =SUM(I22:R22) -> 6460000
F24: EBIT - Earnings Before Interest & Tax | I24: =I22-I19 -> -108000 | J24: =J22-J19 -> 119000 | K24: =K22-K19 -> 329000 | L24: =L22-L19 -> 559000 | M24: =M22-M19 -> 659000 | N24: =N22-N19 -> 667000 | O24: =O22-O19 -> 715000 | P24: =P22-P19 -> 755000 | ... R24: =R22-R19 -> 755000 | S24: =SUM(I24:R24) -> 5205000
F27: Fiscal year | H27: Total | I27: =O10 -> 2026 | J27: =O10+1 -> 2027 | K27: =O10+2 -> 2028 | L27: =O10+3 -> 2029 | M27: =O10+4 -> 2030 | N27: =O10+5 -> 2031 | O27: =O10+6 -> 2032 | P27: =O10+7 -> 2033 | Q27: =O10+8 -> 2034 | R27: =O10+9 -> 2035 | S27: Total
C28: II. Discounted EVA
F29: Non-capitalizable efforts | I29: ='Costs & Benefits'!J125 -> 100000 | J29: ='Costs & Benefits'!K125 -> 75000 | K29: ='Costs & Benefits'!L125 -> 75000 | L29: ='Costs & Benefits'!M125 -> 75000 | M29: ='Costs & Benefits'!N125 -> 75000 | N29: ='Costs & Benefits'!O125 -> 75000 | O29: ='Costs & Benefits'!P125 -> 75000 | P29: ='Costs & Benefits'!Q125 -> 75000 | ... R29: ='Costs & Benefits'!S125 -> 75000 | S29: =SUM(I29:R29) -> 775000
F30: Depreciations | I30: ='Costs & Benefits'!J126 -> 8000 | J30: ='Costs & Benefits'!K126 -> 56000 | K30: ='Costs & Benefits'!L126 -> 96000 | L30: ='Costs & Benefits'!M126 -> 96000 | M30: ='Costs & Benefits'!N126 -> 96000 | N30: ='Costs & Benefits'!O126 -> 88000 | O30: ='Costs & Benefits'!P126 -> 40000 | P30: ='Costs & Benefits'!Q126 -> 0 | ... R30: ='Costs & Benefits'!S126 -> 0 | S30: =SUM(I30:R30) -> 480000
F31: Benefit | I31: ='Costs & Benefits'!J127 -> 0 | J31: 250000 | K31: 500000 | L31: 730000 | M31: 830000 | N31: 830000 | O31: 830000 | P31: 830000 | Q31: 830000 | R31: 830000 | S31: =SUM(I31:R31) -> 6460000
F32: EBIT - Earnings before Interest & Tax | I32: ='Costs & Benefits'!J128 -> -108000 | J32: ='Costs & Benefits'!K128 -> 119000 | K32: ='Costs & Benefits'!L128 -> 329000 | L32: ='Costs & Benefits'!M128 -> 559000 | M32: ='Costs & Benefits'!N128 -> 659000 | N32: ='Costs & Benefits'!O128 -> 667000 | O32: ='Costs & Benefits'!P128 -> 715000 | P32: ='Costs & Benefits'!Q128 -> 755000 | ... R32: ='Costs & Benefits'!S128 -> 755000 | S32: =SUM(I32:R32) -> 5205000
F33: Calculated Tax | I33: ='Costs & Benefits'!J129 -> 29093.782 | J33: ='Costs & Benefits'!K129 -> -32057.037 | K33: ='Costs & Benefits'!L129 -> -88628.28 | L33: ='Costs & Benefits'!M129 -> -150587.26 | M33: ='Costs & Benefits'!N129 -> -177525.95 | N33: ='Costs & Benefits'!O129 -> -179681.04 | O33: ='Costs & Benefits'!P129 -> -192611.61 | P33: ='Costs & Benefits'!Q129 -> -203387.09 | ... R33: ='Costs & Benefits'!S129 -> -203387.09 | S33: =SUM(I33:R33) -> -1402158.7
F34: NOPAT - Net operating profit after Tax | I34: ='Costs & Benefits'!J130 -> -78906.218 | J34: ='Costs & Benefits'!K130 -> 86942.963 | K34: ='Costs & Benefits'!L130 -> 240371.72 | L34: ='Costs & Benefits'!M130 -> 408412.74 | M34: ='Costs & Benefits'!N130 -> 481474.05 | N34: ='Costs & Benefits'!O130 -> 487318.96 | O34: ='Costs & Benefits'!P130 -> 522388.39 | P34: ='Costs & Benefits'!Q130 -> 551612.91 | ... R34: ='Costs & Benefits'!S130 -> 551612.91 | S34: =SUM(I34:R34) -> 3802841.3
F35: Capital Employed (residual book value from inv.) | I35: ='Costs & Benefits'!J131 -> 72000 | J35: ='Costs & Benefits'!K131 -> 416000 | K35: ='Costs & Benefits'!L131 -> 320000 | L35: ='Costs & Benefits'!M131 -> 224000 | M35: ='Costs & Benefits'!N131 -> 128000 | N35: ='Costs & Benefits'!O131 -> 40000 | O35: ='Costs & Benefits'!P131 -> 0 | P35: ='Costs & Benefits'!Q131 -> 0 | ... R35: ='Costs & Benefits'!S131 -> 0 | S35: =SUM(I35:R35) -> 1200000
F36: Calculation Cost of Capital | I36: ='Costs & Benefits'!J132 -> -4183.5186 | J36: ='Costs & Benefits'!K132 -> -24171.441 | K36: ='Costs & Benefits'!L132 -> -18593.416 | L36: ='Costs & Benefits'!M132 -> -13015.391 | M36: ='Costs & Benefits'!N132 -> -7437.3664 | N36: ='Costs & Benefits'!O132 -> -2324.177 | O36: ='Costs & Benefits'!P132 -> 0 | P36: ='Costs & Benefits'!Q132 -> 0 | ... R36: ='Costs & Benefits'!S132 -> 0 | S36: =SUM(I36:R36) -> -69725.31
F37: EVA per period | I37: ='Costs & Benefits'!J133 -> -83089.737 | J37: ='Costs & Benefits'!K133 -> 62771.522 | K37: ='Costs & Benefits'!L133 -> 221778.3 | L37: ='Costs & Benefits'!M133 -> 395397.35 | M37: ='Costs & Benefits'!N133 -> 474036.69 | N37: ='Costs & Benefits'!O133 -> 484994.78 | O37: ='Costs & Benefits'!P133 -> 522388.39 | P37: ='Costs & Benefits'!Q133 -> 551612.91 | ... R37: ='Costs & Benefits'!S133 -> 551612.91 | S37: =SUM(I37:R37) -> 3733116
E39: Discounted EVA per period | I39: ='Costs & Benefits'!J135 -> -83089.737 | J39: ='Costs & Benefits'!K135 -> 59324.506 | K39: ='Costs & Benefits'!L135 -> 198089.75 | L39: ='Costs & Benefits'!M135 -> 333770.66 | M39: ='Costs & Benefits'!N135 -> 378179.37 | N39: ='Costs & Benefits'!O135 -> 365674.28 | O39: ='Costs & Benefits'!P135 -> 372239.39 | P39: ='Costs & Benefits'!Q135 -> 371479.38 | ... R39: ='Costs & Benefits'!S135 -> 331800.97 | S39: =SUM(I39:R39) -> 2678548.6
E41: Discounted EVA cumulative | I41: ='Costs & Benefits'!J136 -> -83089.737 | J41: ='Costs & Benefits'!K136 -> -23765.231 | K41: 179694.68 | L41: 577352.74 | M41: 914058.33 | N41: 1241123.8 | O41: 1558403.5 | P41: 1895441.1 | Q41: 2246521.2 | R41: 2578322.1 | S41: ='Costs & Benefits'!I136 -> 2678548.6
F44: Basic data for EVA Calculation | I44: Tax Rate: | J44: =+VLOOKUP(J7,'Selection lists'!$A$2:$C$50,2,FALSE) -> 0.26938687 | K44: WACC: | L44: =+VLOOKUP(J7,'Selection lists'!$A$2:$C$50,3,FALSE) -> 0.058104425
C48: III. KPI - Key Performance Indicator
F49: Total costs (all years) | I49: =S19 -> 1255000
F50: Total benefits (all years) | I50: =S22 -> 6460000
F51: EBIT (all years) | I51: =S24 -> 5205000
F52: Discounted EVA (all years) | I52: =S39 -> 2678548.6
F53: ROI (all years) | I53: =IFERROR(S41/'Costs & Benefits'!I147,"") -> 5.5803097
F54: Payback Period (y/m) | I54: =IF('Costs & Benefits'!I142="n/a","n/a",'Costs & Benefits'!I145&"Y "&'Costs & Benefits'!I146&"M") -> 1Y 9M
C58: IV. EVA chart

Sheet Costs & Benefits
H2: IT Business Case 2026 - SYNTHETIC TEST DATA | J2: =L10 -> PRODUCT 3 | Campaign Automation [TEST] | T2: ?
H3: Costs & Benefits
K7: Test Scope | L7: =+Summary!J7 -> Synthetic Test Scope | P7: Project Manager | Q7: =Summary!O7 -> Test Project Manager C
K8: Test Decision ID | L8: =+Summary!J8 -> 1003 | P8: Project Sponsor | Q8: =Summary!O8 -> Test Sponsor C
K9: Project Number | L9: =+Summary!J9 -> TEST-BC-003 | P9: Creation date | Q9: =IF(Summary!O9,Summary!O9,"") -> 46037
K10: Project Name | L10: =+Summary!J10 -> PRODUCT 3 | Campaign Automation [TEST] | P10: Start (FY) | Q10: =Summary!O10 -> 2026
K11: Program Name | L11: =+Summary!J11 -> Synthetic Marketing Program C | P11: Go-Live (FY) | Q11: =IF(Summary!O11,Summary!O11,"") -> 2027
C14: A. Cost Calculation (IT Planning)
G16: Fiscal Year | H16: Type | I16: Short Description | J16: =+J31 -> 2026 | K16: =+K31 -> 2027 | L16: =+L31 -> 2028 | M16: =+M31 -> 2029 | N16: =+N31 -> 2030 | O16: =+O31 -> 2031 | P16: =+P31 -> 2032 | Q16: =+Q31 -> 2033 | ... S16: =+S31 -> 2035
D17: I. | E17: Capitalizable efforts (absolute amounts)
G18: Service category 70: Project Capitalizable
G19: Cash Out (intern) | H19: One-Off | I19: Synthetic internal solution and test-design effort | J19: 150000 | K19: 0 | L19: 0 | M19: 0 | N19: 0 | O19: 0 | P19: 0 | Q19: 0 | R19: 0 | S19: 0
G20: Cash Out (extern) | H20: One-Off | I20: Synthetic external implementation effort | J20: 250000 | K20: 0 | L20: 0 | M20: 0 | N20: 0 | O20: 0 | P20: 0 | Q20: 0 | R20: 0 | S20: 0
G21: Service category 90: Software Licenses
G22: Cash Out (intern) | H22: One-Off | I22: Test integration licences and tooling | J22: 50000 | K22: 0 | L22: 0 | M22: 0 | N22: 0 | O22: 0 | P22: 0 | Q22: 0 | R22: 0 | S22: 0
G23: Local IT/IM (Investments)
G24: Cash Out (extern) | H24: One-Off | I24: Synthetic test-environment setup | J24: 30000 | K24: 0 | L24: 0 | M24: 0 | N24: 0 | O24: 0 | P24: 0 | Q24: 0 | R24: 0 | S24: 0
G26: TOTAL | J26: =J19+J20+J22+J24 -> 480000 | K26: =K19+K20+K22+K24 -> 0 | L26: =L19+L20+L22+L24 -> 0 | M26: =M19+M20+M22+M24 -> 0 | N26: =N19+N20+N22+N24 -> 0 | O26: =O19+O20+O22+O24 -> 0 | P26: =P19+P20+P22+P24 -> 0 | Q26: =Q19+Q20+Q22+Q24 -> 0 | ... S26: =S19+S20+S22+S24 -> 0
G28: Useful life (depreciation) | J28: 5 | K28: If useful life > 5 years please comment
G31: Fiscal Year | H31: Type | I31: Short Description | J31: 2026 | K31: =+J31+1 -> 2027 | L31: =+K31+1 -> 2028 | M31: =+L31+1 -> 2029 | N31: =+M31+1 -> 2030 | O31: =+N31+1 -> 2031 | P31: =+O31+1 -> 2032 | Q31: =+P31+1 -> 2033 | R31: =+Q31+1 -> 2034 | S31: =+R31+1 -> 2035
D32: II. | E32: Non-capitalizable efforts (absolute amounts)
G33: Service Category 10: Project Non Capitalizable
G34: Cash Out (intern) | H34: One-Off | I34: Internal test onboarding and enablement | J34: 50000 | K34: 0 | L34: 0 | M34: 0 | N34: 0 | O34: 0 | P34: 0 | Q34: 0 | R34: 0 | S34: 0
G35: Cash Out (extern) | H35: One-Off | I35: External test rollout and documentation support | J35: 50000 | K35: 0 | L35: 0 | M35: 0 | N35: 0 | O35: 0 | P35: 0 | Q35: 0 | R35: 0 | S35: 0
G36: Service category 30: Support & Maintenance
G37: Cash Out (intern) | H37: Recurrent | I37: Internal test platform support | J37: 0 | K37: 20000 | L37: 20000 | M37: 20000 | N37: 20000 | O37: 20000 | P37: 20000 | Q37: 20000 | R37: 20000 | S37: 20000
G38: Service category 30: SaaS
G39: Cash Out (extern) | H39: Recurrent | I39: Test messaging and automation services | J39: 0 | K39: 35000 | L39: 35000 | M39: 35000 | N39: 35000 | O39: 35000 | P39: 35000 | Q39: 35000 | R39: 35000 | S39: 35000
G40: Service category 30: Maintenance for external Software Licenses
G41: Cash Out (extern) | H41: Recurrent | I41: External maintenance for test integrations | J41: 0 | K41: 20000 | L41: 20000 | M41: 20000 | N41: 20000 | O41: 20000 | P41: 20000 | Q41: 20000 | R41: 20000 | S41: 20000
G42: Service category 40: IOS (Infrastructure Operation Service)
G43: Cash Out (intern) | H43: Recurrent
G44: Service category 50: AS (Application Service)
G45: Cash Out (intern) | H45: Recurrent
G46: Local IT/IM (Costs)
G47: Cash Out (intern) | H47: One-Off
G48: Cash Out (intern) | H48: Recurrent
G50: TOTAL | J50: =J34+J35+J37+J39+J41+J43+J45+J47+J48 -> 100000 | K50: =K34+K35+K37+K39+K41+K43+K45+K47+K48 -> 75000 | L50: =L34+L35+L37+L39+L41+L43+L45+L47+L48 -> 75000 | M50: =M34+M35+M37+M39+M41+M43+M45+M47+M48 -> 75000 | N50: =N34+N35+N37+N39+N41+N43+N45+N47+N48 -> 75000 | O50: =O34+O35+O37+O39+O41+O43+O45+O47+O48 -> 75000 | P50: =P34+P35+P37+P39+P41+P43+P45+P47+P48 -> 75000 | Q50: =Q34+Q35+Q37+Q39+Q41+Q43+Q45+Q47+Q48 -> 75000 | ... S50: =S34+S35+S37+S39+S41+S43+S45+S47+S48 -> 75000
D53: III. | E53: Depreciation (automatic calculation to proof if capitalized efforts categories are added) | J53: =+J16 -> 2026 | K53: =+K16 -> 2027 | L53: =+L16 -> 2028 | M53: =+M16 -> 2029 | N53: =+N16 -> 2030 | O53: =+O16 -> 2031 | P53: =+P16 -> 2032 | Q53: =+Q16 -> 2033 | ... S53: =+S16 -> 2035
G54: ="Investment from "&J53 -> Investment from 2026 | J54: =IF(J$53=$Q$11,SUM($J$19:$S$20),0)+J$22+J$24 -> 80000
G55: ="Depreciation from "&J16-1 -> Depreciation from 2025 | J55: =J54/$J$28/2 -> 8000 | K55: =IF($J$54/$J$28<J56,$J$54/$J$28,J56) -> 16000 | L55: =IF($J$54/$J$28<K56,$J$54/$J$28,K56) -> 16000 | M55: =IF($J$54/$J$28<L56,$J$54/$J$28,L56) -> 16000 | N55: =IF($J$54/$J$28<M56,$J$54/$J$28,M56) -> 16000 | O55: =IF($J$54/$J$28<N56,$J$54/$J$28,N56) -> 8000 | P55: =IF($J$54/$J$28<O56,$J$54/$J$28,O56) -> 0 | Q55: =IF($J$54/$J$28<P56,$J$54/$J$28,P56) -> 0 | R55: =IF($J$54/$J$28<Q56,$J$54/$J$28,Q56) -> 0 | S55: =IF($J$54/$J$28<R56,$J$54/$J$28,R56) -> 0
G56: Residual | J56: =J54-J55 -> 72000 | K56: =J56-K55 -> 56000 | L56: =K56-L55 -> 40000 | M56: =L56-M55 -> 24000 | N56: =M56-N55 -> 8000 | O56: =N56-O55 -> 0 | P56: =O56-P55 -> 0 | Q56: =P56-Q55 -> 0 | R56: =Q56-R55 -> 0 | S56: =R56-S55 -> 0
G57: ="Investment from "&K$53 -> Investment from 2027 | K57: =IF(K$53=$Q$11,SUM($J$19:$S$20),0)+K$22+K$24 -> 400000
G58: ="Depreciation from "&J53 -> Depreciation from 2026 | K58: =K57/$J$28/2 -> 40000 | L58: =IF($K$57/$J$28<K59,$K$57/$J$28,K59) -> 80000 | M58: =IF($K$57/$J$28<L59,$K$57/$J$28,L59) -> 80000 | N58: =IF($K$57/$J$28<M59,$K$57/$J$28,M59) -> 80000 | O58: =IF($K$57/$J$28<N59,$K$57/$J$28,N59) -> 80000 | P58: =IF($K$57/$J$28<O59,$K$57/$J$28,O59) -> 40000 | Q58: =IF($K$57/$J$28<P59,$K$57/$J$28,P59) -> 0 | R58: =IF($K$57/$J$28<Q59,$K$57/$J$28,Q59) -> 0 | S58: =IF($K$57/$J$28<R59,$K$57/$J$28,R59) -> 0
G59: Residual | K59: =K57-K58 -> 360000 | L59: =K59-L58 -> 280000 | M59: =L59-M58 -> 200000 | N59: =M59-N58 -> 120000 | O59: =N59-O58 -> 40000 | P59: =O59-P58 -> 0 | Q59: =P59-Q58 -> 0 | R59: =Q59-R58 -> 0 | S59: =R59-S58 -> 0
G60: ="Investment from "&$L$53 -> Investment from 2028 | L60: =IF(L$53=$Q$11,SUM($J$19:$S$20),0)+L$22+L$24 -> 0
G61: ="Depreciation from "&$K$53 -> Depreciation from 2027 | L61: =L60/$J$28/2 -> 0 | M61: =IF($L$60/$J$28<L62,$L$60/$J$28,L62) -> 0 | N61: =IF($L$60/$J$28<M62,$L$60/$J$28,M62) -> 0 | O61: =IF($L$60/$J$28<N62,$L$60/$J$28,N62) -> 0 | P61: =IF($L$60/$J$28<O62,$L$60/$J$28,O62) -> 0 | Q61: =IF($L$60/$J$28<P62,$L$60/$J$28,P62) -> 0 | R61: =IF($L$60/$J$28<Q62,$L$60/$J$28,Q62) -> 0 | S61: =IF($L$60/$J$28<R62,$L$60/$J$28,R62) -> 0
G62: Residual | L62: =L60-L61 -> 0 | M62: =L62-M61 -> 0 | N62: =M62-N61 -> 0 | O62: =N62-O61 -> 0 | P62: =O62-P61 -> 0 | Q62: =P62-Q61 -> 0 | R62: =Q62-R61 -> 0 | S62: =R62-S61 -> 0
G63: ="Investment from "&M53 -> Investment from 2029 | M63: =IF(M$53=$Q$11,SUM($J$19:$S$20),0)+M$22+M$24 -> 0
G64: ="Depreciation from "&$L$53 -> Depreciation from 2028 | M64: =M63/$J$28/2 -> 0 | N64: =IF($M$63/$J$28<M65,$M$63/$J$28,M65) -> 0 | O64: =IF($M$63/$J$28<N65,$M$63/$J$28,N65) -> 0 | P64: =IF($M$63/$J$28<O65,$M$63/$J$28,O65) -> 0 | Q64: =IF($M$63/$J$28<P65,$M$63/$J$28,P65) -> 0 | R64: =IF($M$63/$J$28<Q65,$M$63/$J$28,Q65) -> 0 | S64: =IF($M$63/$J$28<R65,$M$63/$J$28,R65) -> 0
G65: Residual | M65: =M63-M64 -> 0 | N65: =M65-N64 -> 0 | O65: =N65-O64 -> 0 | P65: =O65-P64 -> 0 | Q65: =P65-Q64 -> 0 | R65: =Q65-R64 -> 0 | S65: =R65-S64 -> 0
G66: ="Investment from "&N53 -> Investment from 2030 | N66: =IF(N$53=$Q$11,SUM($J$19:$S$20),0)+N$22+N$24 -> 0
G67: ="Depreciation from "&$M$53 -> Depreciation from 2029 | N67: =N66/$J$28/2 -> 0 | O67: =IF($N$66/$J$28<N68,$N$66/$J$28,N68) -> 0 | P67: =IF($N$66/$J$28<O68,$N$66/$J$28,O68) -> 0 | Q67: =IF($N$66/$J$28<P68,$N$66/$J$28,P68) -> 0 | R67: =IF($N$66/$J$28<Q68,$N$66/$J$28,Q68) -> 0 | S67: =IF($N$66/$J$28<R68,$N$66/$J$28,R68) -> 0
G68: Residual | N68: =N66-N67 -> 0 | O68: =N68-O67 -> 0 | P68: =O68-P67 -> 0 | Q68: =P68-Q67 -> 0 | R68: =Q68-R67 -> 0 | S68: =R68-S67 -> 0
G69: ="Investment from "&O53 -> Investment from 2031 | O69: =IF(O$53=$Q$11,SUM($J$19:$S$20),0)+O$22+O$24 -> 0
G70: ="Depreciation from "&$N$53 -> Depreciation from 2030 | O70: =O69/$J$28/2 -> 0 | P70: =IF($O$69/$J$28<O71,$O$69/$J$28,O71) -> 0 | Q70: =IF($O$69/$J$28<P71,$O$69/$J$28,P71) -> 0 | R70: =IF($O$69/$J$28<Q71,$O$69/$J$28,Q71) -> 0 | S70: =IF($O$69/$J$28<R71,$O$69/$J$28,R71) -> 0
G71: Residual | O71: =O69-O70 -> 0 | P71: =O71-P70 -> 0 | Q71: =P71-Q70 -> 0 | R71: =Q71-R70 -> 0 | S71: =R71-S70 -> 0
G72: ="Investment from "&P53 -> Investment from 2032 | P72: =IF(P$53=$Q$11,SUM($J$19:$S$20),0)+P$22+P$24 -> 0
G73: ="Depreciation from "&$O$53 -> Depreciation from 2031 | P73: =P72/$J$28/2 -> 0 | Q73: =IF($P$72/$J$28<P74,$P$72/$J$28,P74) -> 0 | R73: =IF($P$72/$J$28<Q74,$P$72/$J$28,Q74) -> 0 | S73: =IF($P$72/$J$28<R74,$P$72/$J$28,R74) -> 0
G74: Residual | P74: =P72-P73 -> 0 | Q74: =P74-Q73 -> 0 | R74: =Q74-R73 -> 0 | S74: =R74-S73 -> 0
G75: ="Investment from "&Q53 -> Investment from 2033 | Q75: =IF(Q$53=$Q$11,SUM($J$19:$S$20),0)+Q$22+Q$24 -> 0
G76: ="Depreciation from "&$P$53 -> Depreciation from 2032 | Q76: =Q75/$J$28/2 -> 0 | R76: =IF($Q$75/$J$28<Q77,$Q$75/$J$28,Q77) -> 0 | S76: =IF($Q$75/$J$28<R77,$Q$75/$J$28,R77) -> 0
G77: Residual | Q77: =Q75-Q76 -> 0 | R77: =Q77-R76 -> 0 | S77: =R77-S76 -> 0
G78: ="Investment from "&R53 -> Investment from 2034 | R78: =IF(R$53=$Q$11,SUM($J$19:$S$20),0)+R$22+R$24 -> 0
G79: ="Depreciation from "&$Q$53 -> Depreciation from 2033 | R79: =R78/$J$28/2 -> 0 | S79: =IF($R$78/$J$28<R80,$R$78/$J$28,R80) -> 0
G80: Residual | R80: =R78-R79 -> 0 | S80: =R80-S79 -> 0
G81: ="Investment from "&S53 -> Investment from 2035 | S81: =IF(S$53=$Q$11,SUM($J$19:$S$20),0)+S$22+S$24 -> 0
G82: ="Depreciation from "&$R$53 -> Depreciation from 2034 | S82: =S81/$J$28/2 -> 0
G83: Residual | S83: =S81-S82 -> 0
G84: TOTAL | J84: =J55+J58+J61+J64+J67+J70+J73+J76+J79+J82 -> 8000 | K84: =K55+K58+K61+K64+K67+K70+K73+K76+K79+K82 -> 56000 | L84: =L55+L58+L61+L64+L67+L70+L73+L76+L79+L82 -> 96000 | M84: =M55+M58+M61+M64+M67+M70+M73+M76+M79+M82 -> 96000 | N84: =N55+N58+N61+N64+N67+N70+N73+N76+N79+N82 -> 96000 | O84: =O55+O58+O61+O64+O67+O70+O73+O76+O79+O82 -> 88000 | P84: =P55+P58+P61+P64+P67+P70+P73+P76+P79+P82 -> 40000 | Q84: =Q55+Q58+Q61+Q64+Q67+Q70+Q73+Q76+Q79+Q82 -> 0 | ... S84: =S55+S58+S61+S64+S67+S70+S73+S76+S79+S82 -> 0
C86: A. Cost Calculation (IT Planning) | I86: Total Costs | J86: =J84+J50 -> 108000 | K86: =K84+K50 -> 131000 | L86: =L84+L50 -> 171000 | M86: =M84+M50 -> 171000 | N86: =N84+N50 -> 171000 | O86: =O84+O50 -> 163000 | P86: =P84+P50 -> 115000 | Q86: =Q84+Q50 -> 75000 | ... S86: =S84+S50 -> 75000
C89: B. Benefit Calculation (Business Planning)
G91: Fiscal Year | H91: Type | I91: Short Description | J91: =J31 -> 2026 | K91: =K31 -> 2027 | L91: =L31 -> 2028 | M91: =M31 -> 2029 | N91: =N31 -> 2030 | O91: =O31 -> 2031 | P91: =P31 -> 2032 | Q91: =Q31 -> 2033 | ... S91: =S31 -> 2035
D92: I. | E92: Sales Benefits
G93: Sales Benefits
I94: Synthetic incremental value from automated test journeys | J94: 0 | K94: 200000 | L94: 400000 | M94: 600000 | N94: 700000 | O94: 700000 | P94: 700000 | Q94: 700000 | R94: 700000 | S94: 700000
G101: TOTAL | J101: =SUM(J94:J99) -> 0 | K101: =SUM(K94:K99) -> 200000 | L101: =SUM(L94:L99) -> 400000 | M101: =SUM(M94:M99) -> 600000 | N101: =SUM(N94:N99) -> 700000 | O101: =SUM(O94:O99) -> 700000 | P101: =SUM(P94:P99) -> 700000 | Q101: =SUM(Q94:Q99) -> 700000 | ... S101: =SUM(S94:S99) -> 700000
G103: Fiscal Year | H103: Type | I103: Short Description | J103: =J31 -> 2026 | K103: =K31 -> 2027 | L103: =L31 -> 2028 | M103: =M31 -> 2029 | N103: =N31 -> 2030 | O103: =O31 -> 2031 | P103: =P31 -> 2032 | Q103: =Q31 -> 2033 | ... S103: =S31 -> 2035
D104: II. | E104: Cost Savings (absolute amounts)
G105: Cost Savings
I106: Reduced manual setup effort in the test process | J106: 0 | K106: 30000 | L106: 60000 | M106: 80000 | N106: 80000 | O106: 80000 | P106: 80000 | Q106: 80000 | R106: 80000 | S106: 80000
I107: Reduced duplicated test-template and integration effort | J107: 0 | K107: 20000 | L107: 40000 | M107: 50000 | N107: 50000 | O107: 50000 | P107: 50000 | Q107: 50000 | R107: 50000 | S107: 50000
G113: TOTAL | J113: =SUM(J106:J111) -> 0 | K113: =SUM(K106:K111) -> 50000 | L113: =SUM(L106:L111) -> 100000 | M113: =SUM(M106:M111) -> 130000 | N113: =SUM(N106:N111) -> 130000 | O113: =SUM(O106:O111) -> 130000 | P113: =SUM(P106:P111) -> 130000 | Q113: =SUM(Q106:Q111) -> 130000 | ... S113: =SUM(S106:S111) -> 130000
D115: III. | E115: Additional non-monetary Benefits
G116: Non-quantitative Benefits
G117: Synthetic qualitative benefits: repeatable campaign tests; faster setup; consistent measurement; no use of production customer data.
C119: B. Benefit Calculation (Business Planning) Total Costs | J119: =J101+J113 -> 0 | K119: =K101+K113 -> 250000 | L119: =L101+L113 -> 500000 | M119: =M101+M113 -> 730000 | N119: =N101+N113 -> 830000 | O119: =O101+O113 -> 830000 | P119: =P101+P113 -> 830000 | Q119: =Q101+Q113 -> 830000 | ... S119: =S101+S113 -> 830000
C122: C. Calculation of Discounted EVA
I124: TOTAL | J124: =+J103 -> 2026 | K124: =+K103 -> 2027 | L124: =+L103 -> 2028 | M124: =+M103 -> 2029 | N124: =+N103 -> 2030 | O124: =+O103 -> 2031 | P124: =+P103 -> 2032 | Q124: =+Q103 -> 2033 | ... S124: =+S103 -> 2035
G125: Non-capitalizable efforts | I125: =SUM(J125:S125) -> 775000 | J125: =J50 -> 100000 | K125: =K50 -> 75000 | L125: =L50 -> 75000 | M125: =M50 -> 75000 | N125: =N50 -> 75000 | O125: =O50 -> 75000 | P125: =P50 -> 75000 | Q125: =Q50 -> 75000 | ... S125: =S50 -> 75000 | U125: -1
G126: Depreciations | I126: =SUM(J126:S126) -> 480000 | J126: =J84 -> 8000 | K126: =K84 -> 56000 | L126: =L84 -> 96000 | M126: =M84 -> 96000 | N126: =N84 -> 96000 | O126: =O84 -> 88000 | P126: =P84 -> 40000 | Q126: =Q84 -> 0 | ... S126: =S84 -> 0 | U126: (2)
G127: Total Benefits | I127: =SUM(J127:S127) -> 6460000 | J127: =J119 -> 0 | K127: =K119 -> 250000 | L127: =L119 -> 500000 | M127: =M119 -> 730000 | N127: =N119 -> 830000 | O127: =O119 -> 830000 | P127: =P119 -> 830000 | Q127: =Q119 -> 830000 | ... S127: =S119 -> 830000 | U127: (3)
G128: EBIT - Earnings before Interest & Tax | I128: =SUM(J128:S128) -> 5205000 | J128: =J127-J126-J125 -> -108000 | K128: =K127-K126-K125 -> 119000 | L128: =L127-L126-L125 -> 329000 | M128: =M127-M126-M125 -> 559000 | N128: =N127-N126-N125 -> 659000 | O128: =O127-O126-O125 -> 667000 | P128: =P127-P126-P125 -> 715000 | Q128: =Q127-Q126-Q125 -> 755000 | ... S128: =S127-S126-S125 -> 755000 | U128: (4) = + (3) - (2) - (1)
G129: Calculation Tax | I129: =SUM(J129:S129) -> -1402158.7 | J129: =J128*-Summary!$J$44 -> 29093.782 | K129: =K128*-Summary!$J$44 -> -32057.037 | L129: =L128*-Summary!$J$44 -> -88628.28 | M129: =M128*-Summary!$J$44 -> -150587.26 | N129: =N128*-Summary!$J$44 -> -177525.95 | O129: =O128*-Summary!$J$44 -> -179681.04 | P129: =P128*-Summary!$J$44 -> -192611.61 | Q129: =Q128*-Summary!$J$44 -> -203387.09 | ... S129: =S128*-Summary!$J$44 -> -203387.09 | U129: (5) = - Tax Rate x (4)
G130: NOPAT - Net operating profit after Tax | I130: =SUM(J130:S130) -> 3802841.3 | J130: =J128+J129 -> -78906.218 | K130: =K128+K129 -> 86942.963 | L130: =L128+L129 -> 240371.72 | M130: =M128+M129 -> 408412.74 | N130: =N128+N129 -> 481474.05 | O130: =O128+O129 -> 487318.96 | P130: =P128+P129 -> 522388.39 | Q130: =Q128+Q129 -> 551612.91 | ... S130: =S128+S129 -> 551612.91 | U130: (6) = (5) - (4)
G131: Capital Employed | I131: =SUM(J131:S131) -> 1200000 | J131: =J56 -> 72000 | K131: =K56+K59 -> 416000 | L131: =L56+L59+L62 -> 320000 | M131: =M56+M59+M62+M65 -> 224000 | N131: =N56+N59+N62+N65+N68 -> 128000 | O131: =O56+O59+O62+O65+O68+O71 -> 40000 | P131: =P56+P59+P62+P65+P68+P71+P74 -> 0 | Q131: =Q56+Q59+Q62+Q65+Q68+Q71+Q74+Q77 -> 0 | R131: =R56+R59+R62+R65+R68+R71+R74+R77+R80 -> 0 | S131: =S56+S59+S62+S65+S68+S71+S74+S77+S80+S83 -> 0 | U131: (7)
G132: Calculation Cost of Capital | I132: =SUM(J132:S132) -> -69725.31 | J132: =-J131*Summary!$L$44 -> -4183.5186 | K132: =-K131*Summary!$L$44 -> -24171.441 | L132: =-L131*Summary!$L$44 -> -18593.416 | M132: =-M131*Summary!$L$44 -> -13015.391 | N132: =-N131*Summary!$L$44 -> -7437.3664 | O132: =-O131*Summary!$L$44 -> -2324.177 | P132: =-P131*Summary!$L$44 -> 0 | Q132: =-Q131*Summary!$L$44 -> 0 | ... S132: =-S131*Summary!$L$44 -> 0 | U132: (8) = (7) x WACC
G133: Calculation EVA per period | I133: =SUM(J133:S133) -> 3733116 | J133: =J130+J132 -> -83089.737 | K133: =K130+K132 -> 62771.522 | L133: =L130+L132 -> 221778.3 | M133: =M130+M132 -> 395397.35 | N133: =N130+N132 -> 474036.69 | O133: =O130+O132 -> 484994.78 | P133: =P130+P132 -> 522388.39 | Q133: =Q130+Q132 -> 551612.91 | ... S133: =S130+S132 -> 551612.91 | U133: (9) = (6) + (8)
C135: Calculation of discounted EVA | I135: =SUM(J135:S135) -> 2678548.6 | J135: =J133/(1+Summary!$L$44)^0 -> -83089.737 | K135: =K133/(1+Summary!$L$44)^1 -> 59324.506 | L135: =L133/(1+Summary!$L$44)^2 -> 198089.75 | M135: =M133/(1+Summary!$L$44)^3 -> 333770.66 | N135: =N133/(1+Summary!$L$44)^4 -> 378179.37 | O135: =O133/(1+Summary!$L$44)^5 -> 365674.28 | P135: =P133/(1+Summary!$L$44)^6 -> 372239.39 | Q135: =Q133/(1+Summary!$L$44)^7 -> 371479.38 | R135: =R133/(1+Summary!$L$44)^8 -> 351080.07 | S135: =S133/(1+Summary!$L$44)^9 -> 331800.97
C136: Calculation of cumulative EVA | I136: =I135 -> 2678548.6 | J136: =J135 -> -83089.737 | K136: =J136+K135 -> -23765.231 | L136: =K136+L135 -> 174324.52 | M136: =L136+M135 -> 508095.18 | N136: =M136+N135 -> 886274.55 | O136: =N136+O135 -> 1251948.8 | P136: =O136+P135 -> 1624188.2 | Q136: =P136+Q135 -> 1995667.6 | R136: =Q136+R135 -> 2346747.7 | S136: =R136+S135 -> 2678548.6
...

Sheet Project Description

Sheet Project Cost Description

Sheet Benefit Calculation

Sheet List of Demands
B7: Demand Category | C7: Demand Number | D7: Demand Title | E7: Demand Description | F7: Benefit Description | G7: Business Risk if not implemented | H7: Demand Costs
B8: Business | C8: 1 | D8: PRODUCT 3 | Campaign Automation [TEST] | E8: Implement a synthetic campaign-automation scenario using generated customer profiles, sample segments and fictitious responses. | F8: Tests orchestration, measurement and comparison logic without using real customer, campaign or behavioural data. | G8: The test environment would not cover the intended automation and measurement paths. | H8: See Costs & Benefits
B9: Rollout | C9: 2 | D9: Test rollout and adoption | E9: Enable synthetic regions and test users with reusable templates and a standard support model. | F9: Makes campaign tests repeatable and comparable across synthetic regions. | G9: Test execution would be fragmented and results less comparable. | H9: Included in project costs

Sheet Demand N°1 Benefit
B8: PRODUCT 3 | Campaign Automation [TEST]
B12: As-is: synthetic campaigns are prepared in separate test steps with limited standardisation and measurement.
B20: To-be: Product 3 orchestrates generated profiles, sample messages, landing pages and synthetic responses in one repeatable test flow.
B27: Synthetic qualitative benefits: repeatable campaign tests; faster setup; consistent measurement; no use of production customer data.

Sheet Demand N°2 Benefit
B8: Test rollout and adoption
B12: As-is: test setup and adoption differ across synthetic regions.
B20: To-be: all synthetic regions use common templates, training and test-support procedures.
B27: Faster test rollout, less duplicated setup work and more comparable results.

Sheet Definition_Service Categories
B1: Definition of capitalizable and non capitalizable efforts
B3: Project Non Capitalizable | C3: SC 10
B4: Strategy & Analysis
B5: - Project initiation - Project management (planning, controlling, reporting) - Documentation of research results - Proof of concept
B6: Training
B7: - Release change - Preparation of training material & training - On-site support - Project management activities for this tasks
B8: Project Capitalizable | C8: SC 70
B9: Design & Implementation
B10: - Functional & technical specification - Solution design - all software development services until introduction - Test case definition - Execution of tests (module test, functional test, integration test, user acceptance test etc.) - Migration - Solution documentation - Project management activity for this tasks
B11: Introduction
B12: - All software development services during introduction - Customer specific adaptions - Rollout of software solution selective or area-wide - Harmonisation of software solutions - Go live - Project management activity for this tasks
B13: Support & Maintenance (non capitalizable) | C13: SC 30
B14: 2nd Level-Support
B15: - Phase: after go live - Analyses, management of bug fixing - Specification of the occured bugs - Forwording of bugs if required - Concerns also OSS and R&D for SAP
B16: Maintenance
B17: - Phase: after go live - Bug fixing - Performance tuning based on technical necessities - Innovation based on further technical developments
B18: Infrastructure Operations (non capitalizable) | C18: SC 40
B19: - Services of the synthetic test IT unit "Infrastructure Operations"
B20: Application Operations (non capitalizable) | C20: SC 50
B21: - Services of the synthetic test IT unit "Application Operations"
B22: Software Licences (capitalizable) | C22: SC 90
B23: - License costs for external standard software, e.g. Oracle, Tivoli, SAP, SAF etc. - Maintance of external software belongs to the service category 30
